{
  "description": "A man in a tuxedo top and plaid pants is depicted falling headfirst from a can labeled \"NUTS\" towards two green snakes. This surreal scene offers a literal and absurd interpretation of the idiom \"going nuts,\" where a person emerges directly from a can of nuts. The snakes appear surprised or amused by the man's sudden appearance. The situation is highly unusual, featuring an incongruously dressed man and talking snakes reacting to a bizarre event.",
  "caption": "",
  "other_text": [
    {
      "location": "Top center",
      "text": "12/5/80"
    },
    {
      "location": "On the can",
      "text": "NUTS"
    },
    {
      "location": "Bottom left",
      "text": "Larson"
    }
  ],
  "in": 376,
  "out": 193,
  "think": 727
}