{
  "description": "A massive, tangled pile of bicycles sits beside a doghouse, with a dog's paws visible from the entrance. This bizarre accumulation implies the dog is responsible for incapacitating a multitude of bikes, likely those used for newspaper delivery. The surreal scale of the bicycle graveyard provides an absurd visual contrast to the small, ordinary doghouse. This scene offers an ironic exaggeration of the common interaction between dogs and delivery vehicles, depicting a large-scale, inexplicable conflict.",
  "caption": "",
  "other_text": [
    {
      "location": "top center",
      "text": "7/7/81"
    },
    {
      "location": "bottom left",
      "text": "Larson"
    },
    {
      "location": "on newspaper in bike pile",
      "text": "NEWS"
    }
  ],
  "in": 377,
  "out": 196,
  "think": 962
}