{
  "description": "The scene depicts a colossal ape perched atop a city skyscraper, a familiar image from classic cinema, yet this creature displays a puzzled expression and shrugs its shoulders with open palms. Two biplanes circle overhead, typically symbols of human resistance in such narratives, but the ape's seemingly confused reaction subverts the expected confrontation. This juxtaposition of the grand, fantastical scenario with the creature's mundane, human-like bewilderment introduces an element of the absurd and surreal. The ape appears less like a destructive force and more like a bewildered participant in a situation beyond its understanding. The image plays on the viewer's expectations of the giant monster trope by presenting the ape as strangely passive and questioning.",
  "caption": "",
  "other_text": [
    {
      "location": "top_center",
      "text": "4/8/82"
    },
    {
      "location": "bottom_right",
      "text": "Larson"
    }
  ],
  "in": 377,
  "out": 221,
  "think": 672
}